lobster/tools/gtest/__init__.py
lobster/tools/gtest/gtest.py
bmw_lobster_tool_gtest-1.0.2.dist-info/METADATA
bmw_lobster_tool_gtest-1.0.2.dist-info/WHEEL
bmw_lobster_tool_gtest-1.0.2.dist-info/entry_points.txt
bmw_lobster_tool_gtest-1.0.2.dist-info/top_level.txt
bmw_lobster_tool_gtest-1.0.2.dist-info/RECORD
