Metadata-Version: 2.4
Name: bmw-lobster-tool-gtest
Version: 1.0.2
Summary: LOBSTER Tool for GoogleTest
Home-page: https://github.com/bmw-software-engineering/lobster
Author: Bayerische Motoren Werke Aktiengesellschaft (BMW AG)
Author-email: philipp.wullstein-kammler@bmw.de
License: GNU Affero General Public License v3
Project-URL: Bug Tracker, https://github.com/bmw-software-engineering/lobster/issues
Project-URL: Documentation, https://github.com/pages/bmw-software-engineering/lobster/
Project-URL: Source Code, https://github.com/bmw-software-engineering/lobster
Classifier: Development Status :: 5 - Production/Stable
Classifier: Environment :: Console
Classifier: Intended Audience :: Developers
Classifier: License :: OSI Approved :: GNU Affero General Public License v3 or later (AGPLv3+)
Classifier: Topic :: Documentation
Classifier: Topic :: Software Development
Requires-Python: >=3.7, <4
Requires-Dist: bmw-lobster-core>=1.0.2
Dynamic: author
Dynamic: author-email
Dynamic: classifier
Dynamic: description
Dynamic: description-content-type
Dynamic: home-page
Dynamic: license
Dynamic: project-url
Dynamic: requires-dist
Dynamic: requires-python
Dynamic: summary
